d_lottery.v
module lottery (
    input clk, input reset, input luckybit, input write, input stop,
    output [4:0] winner, output [4:0] id, output full
);

reg [31:0] lucky_queue;
reg full = 1'b0;
reg [4:0] id = 5'b0;
reg [4:0] winner = 5'bx;
wire [4:0] winner_temp = 5'bx;

always @(posedge write or reset) begin
    if (reset == 1) begin
        lucky_queue = 32'b0;
        id = 5'b0;
    end
    else if(id < 32) begin
        lucky_queue[id] = luckybit;
        id = id + 1;
    end
    else begin
        full = 1;
    end
end

winner_generator winner_generator(
    .lucky_queue(lucky_queue),
    .id(id),
    .stop(stop),
    .clk(clk),
    .reset(reset),
    .data(winner_temp),
    .full(full)
);

always @(posedge clk or reset) begin
    if (reset == 1) begin
        winner = 5'bx;
    end
    else if (winner_temp != 5'b0 && (stop || full)) begin
        winner = winner_temp;
    end
end

endmodule

module winner_generator (
    lucky_queue, id, stop, clk, reset, data, full
);
    input [31:0] lucky_queue;
    input [4:0] id;
    input stop;
    input clk;
    input reset;
    output [4:0] data;
    reg [4:0] data;
    input full;

reg [4:0] data_next;

always @(*) begin
  data_next[4] = data[4]^data[1];
  data_next[3] = data[3]^data[0];
  data_next[2] = data[2]^data_next[4];
  data_next[1] = data[1]^data_next[3];
  data_next[0] = data[0]^data_next[2];
end

always @(posedge clk or reset)
  if(reset || id<5 || data == 5'b0)
    data <= {lucky_queue[$random%id], lucky_queue[$random%id], lucky_queue[$random%id], lucky_queue[$random%id], lucky_queue[$random%id]};
  else if(!(stop || full))
    data <= data_next;
    
endmodule

lottery_tb.v
`include "d_lottery.v"
`default_nettype none

module tb_lottery;
reg clk;
reg reset;
reg luckybit, write;
reg stop;
wire [4:0] winner, id;
wire [31:0] lucky_queue;
wire full;

lottery dut ( .clk(clk), .reset(reset), .luckybit(luckybit), .write(write), .stop(stop), .winner(winner), .id(id), .full(full) );

initial begin
    clk = 0;
    forever #5 clk = ~clk;
end

initial begin
    $dumpfile("d_lottery.vcd");
    $dumpvars(0, tb_lottery);
end

initial begin
    reset = 1;
    stop = 0;
    write = 0;
    #10 reset = 0;

    for (integer k  = 0; k<33 ; k=k+1 ) begin
        luckybit = $random%2;
        #5 write = 1;
        #7 write = 0;
    end 

    #5 stop = 1;
    #5 $finish;
end

endmodule
`default_nettype wire

d_lottery.vcd
$date
	Fri May 12 21:33:44 2023
$end
$version
	Icarus Verilog
$end
$timescale
	1s
$end
$scope module tb_lottery $end
$var wire 5 ! winner [4:0] $end
$var wire 5 " id [4:0] $end
$var wire 1 # full $end
$var reg 1 $ clk $end
$var reg 1 % luckybit $end
$var reg 1 & reset $end
$var reg 1 ' stop $end
$var reg 1 ( write $end
$scope module dut $end
$var wire 1 $ clk $end
$var wire 1 % luckybit $end
$var wire 1 & reset $end
$var wire 1 ' stop $end
$var wire 5 ) winner_temp [4:0] $end
$var wire 1 ( write $end
$var reg 1 # full $end
$var reg 5 * id [4:0] $end
$var reg 32 + lucky_queue [31:0] $end
$var reg 5 , winner [4:0] $end
$scope module winner_generator $end
$var wire 1 $ clk $end
$var wire 1 # full $end
$var wire 5 - id [4:0] $end
$var wire 32 . lucky_queue [31:0] $end
$var wire 1 & reset $end
$var wire 1 ' stop $end
$var reg 5 / data [4:0] $end
$var reg 5 0 data_next [4:0] $end
$upscope $end
$upscope $end
$scope begin $ivl_for_loop0 $end
$var integer 32 1 k [31:0] $end
$upscope $end
$upscope $end
$enddefinitions $end
$comment Show the parameter values. $end
$dumpall
$end
#0
$dumpvars
bx 1
bx 0
bx /
b0 .
b0 -
bx ,
b0 +
b0 *
bx )
0(
0'
1&
x%
0$
0#
b0 "
bx !
$end
#5
1$
#10
b0 0
b0 /
b1 "
b1 *
b1 -
0$
0%
b0 1
0&
#15
b10 "
b10 *
b10 -
1$
1(
#20
0$
#22
1%
b1 1
0(
#25
1$
#27
b11 "
b11 *
b11 -
b100 +
b100 .
1(
#30
0$
#34
b10 1
0(
#35
b1011 0
b1 /
1$
#39
b100 "
b100 *
b100 -
b1100 +
b1100 .
1(
#40
0$
#45
b10110 0
b1011 /
1$
#46
b11 1
0(
#50
0$
#51
b101 "
b101 *
b101 -
b11100 +
b11100 .
1(
#55
b111 0
b10110 /
1$
#58
b100 1
0(
#60
0$
#63
b110 "
b110 *
b110 -
b111100 +
b111100 .
1(
#65
b11001 0
b111 /
1$
#70
0$
b101 1
0(
#75
b10100 0
b11001 /
b111 "
b111 *
b111 -
b1111100 +
b1111100 .
1$
1(
#80
0$
#82
b110 1
0(
#85
b10000 0
b10100 /
1$
#87
b1000 "
b1000 *
b1000 -
b11111100 +
b11111100 .
1(
#90
0$
#94
0%
b111 1
0(
#95
b10101 0
b10000 /
1$
#99
b1001 "
b1001 *
b1001 -
1(
#100
0$
#105
b11011 0
b10101 /
1$
#106
b1000 1
0(
#110
0$
#111
b1010 "
b1010 *
b1010 -
1(
#115
b11 0
b11011 /
1$
#118
1%
b1001 1
0(
#120
0$
#123
b1011 "
b1011 *
b1011 -
b10011111100 +
b10011111100 .
1(
#125
b11100 0
b11 /
1$
#130
0$
b1010 1
0(
#135
b11010 0
b11100 /
b1100 "
b1100 *
b1100 -
b110011111100 +
b110011111100 .
1$
1(
#140
0$
#142
b1011 1
0(
#145
b1000 0
b11010 /
1$
#147
b1101 "
b1101 *
b1101 -
b1110011111100 +
b1110011111100 .
1(
#150
0$
#154
0%
b1100 1
0(
#155
b1010 0
b1000 /
1$
#159
b1110 "
b1110 *
b1110 -
1(
#160
0$
#165
b11101 0
b1010 /
1$
#166
b1101 1
0(
#170
0$
#171
b1111 "
b1111 *
b1111 -
1(
#175
b10001 0
b11101 /
1$
#178
b1110 1
0(
#180
0$
#183
b10000 "
b10000 *
b10000 -
1(
#185
b11110 0
b10001 /
1$
#190
0$
b1111 1
0(
#195
b1101 0
b11110 /
b10001 "
b10001 *
b10001 -
1$
1(
#200
0$
#202
b10000 1
0(
#205
b100 0
b1101 /
1$
#207
b10010 "
b10010 *
b10010 -
1(
#210
0$
#214
1%
b10001 1
0(
#215
b101 0
b100 /
1$
#219
b10011 "
b10011 *
b10011 -
b1000001110011111100 +
b1000001110011111100 .
1(
#220
0$
#225
b1110 0
b101 /
1$
#226
0%
b10010 1
0(
#230
0$
#231
b10100 "
b10100 *
b10100 -
1(
#235
b11000 0
b1110 /
1$
#238
b10011 1
0(
#240
0$
#243
b10101 "
b10101 *
b10101 -
1(
#245
b11111 0
b11000 /
1$
#250
0$
1%
b10100 1
0(
#255
b110 0
b11111 /
b10110 "
b10110 *
b10110 -
b1001000001110011111100 +
b1001000001110011111100 .
1$
1(
#260
0$
#262
b10101 1
0(
#265
b10010 0
b110 /
1$
#267
b10111 "
b10111 *
b10111 -
b11001000001110011111100 +
b11001000001110011111100 .
1(
#270
0$
#274
0%
b10110 1
0(
#275
b10 0
b10010 /
1$
#279
b11000 "
b11000 *
b11000 -
1(
#280
0$
#285
b10111 0
b10 /
1$
#286
b10111 1
0(
#290
0$
#291
b11001 "
b11001 *
b11001 -
1(
#295
b1100 0
b10111 /
1$
#298
b11000 1
0(
#300
0$
#303
b11010 "
b11010 *
b11010 -
1(
#305
b1111 0
b1100 /
1$
#310
0$
b11001 1
0(
#315
b10011 0
b1111 /
b11011 "
b11011 *
b11011 -
1$
1(
#320
0$
#322
b11010 1
0(
#325
b1001 0
b10011 /
1$
#327
b11100 "
b11100 *
b11100 -
1(
#330
0$
#334
1%
b11011 1
0(
#335
b1 0
b1001 /
1$
#339
b11101 "
b11101 *
b11101 -
b10000011001000001110011111100 +
b10000011001000001110011111100 .
1(
#340
0$
#345
b1011 0
b1 /
1$
#346
b11100 1
0(
#350
0$
#351
b11110 "
b11110 *
b11110 -
b110000011001000001110011111100 +
b110000011001000001110011111100 .
1(
#355
b10110 0
b1011 /
1$
#358
b11101 1
0(
#360
0$
#363
b11111 "
b11111 *
b11111 -
b1110000011001000001110011111100 +
b1110000011001000001110011111100 .
1(
#365
b111 0
b10110 /
1$
#370
0$
b11110 1
0(
#375
bx 0
bx /
b0 "
b0 *
b0 -
b11110000011001000001110011111100 +
b11110000011001000001110011111100 .
1$
1(
#380
0$
#382
b11111 1
0(
#385
1$
#387
b1 "
b1 *
b1 -
b11110000011001000001110011111101 +
b11110000011001000001110011111101 .
1(
#390
0$
#394
b100000 1
0(
#395
b110 0
b11111 /
1$
#399
b10 "
b10 *
b10 -
b11110000011001000001110011111111 +
b11110000011001000001110011111111 .
1(
#400
0$
#405
1$
#406
b100001 1
0(
#410
0$
#411
1'
